{
  "annotations": { "list": [] },
  "editable": true,
  "fiscalYearStartMonth": 0,
  "graphTooltip": 0,
  "id": null,
  "links": [],
  "liveNow": false,
  "panels": [
    {
      "collapsed": false,
      "gridPos": { "h": 1, "w": 24, "x": 0, "y": 0 },
      "id": 1,
      "panels": [],
      "title": "Spark Batch Jobs",
      "type": "row"
    },
    {
      "datasource": { "type": "prometheus", "uid": "prometheus" },
      "fieldConfig": {
        "defaults": {
          "color": { "mode": "thresholds" },
          "mappings": [],
          "thresholds": { "mode": "absolute", "steps": [{ "color": "green", "value": null }] },
          "unit": "short"
        },
        "overrides": []
      },
      "gridPos": { "h": 4, "w": 4, "x": 0, "y": 1 },
      "id": 2,
      "options": { "colorMode": "background", "graphMode": "area", "justifyMode": "auto", "orientation": "auto", "reduceOptions": { "calcs": ["lastNotNull"], "fields": "", "values": false }, "textMode": "auto" },
      "targets": [{ "expr": "spark_job_count{status=\"succeeded\"}", "legendFormat": "Succeeded", "refId": "A" }],
      "title": "Successful Jobs",
      "type": "stat"
    },
    {
      "datasource": { "type": "prometheus", "uid": "prometheus" },
      "fieldConfig": {
        "defaults": {
          "color": { "mode": "thresholds" },
          "mappings": [],
          "thresholds": { "mode": "absolute", "steps": [{ "color": "green", "value": null }, { "color": "yellow", "value": 1 }, { "color": "red", "value": 5 }] },
          "unit": "short"
        },
        "overrides": []
      },
      "gridPos": { "h": 4, "w": 4, "x": 4, "y": 1 },
      "id": 3,
      "options": { "colorMode": "background", "graphMode": "area", "justifyMode": "auto", "orientation": "auto", "reduceOptions": { "calcs": ["lastNotNull"], "fields": "", "values": false }, "textMode": "auto" },
      "targets": [{ "expr": "spark_job_count{status=\"failed\"}", "legendFormat": "Failed", "refId": "A" }],
      "title": "Failed Jobs",
      "type": "stat"
    },
    {
      "datasource": { "type": "prometheus", "uid": "prometheus" },
      "fieldConfig": {
        "defaults": {
          "color": { "mode": "thresholds" },
          "mappings": [],
          "thresholds": { "mode": "absolute", "steps": [{ "color": "green", "value": null }] },
          "unit": "s"
        },
        "overrides": []
      },
      "gridPos": { "h": 4, "w": 4, "x": 8, "y": 1 },
      "id": 4,
      "options": { "colorMode": "value", "graphMode": "area", "justifyMode": "auto", "orientation": "auto", "reduceOptions": { "calcs": ["mean"], "fields": "", "values": false }, "textMode": "auto" },
      "targets": [{ "expr": "avg(spark_job_duration_seconds)", "legendFormat": "Avg Duration", "refId": "A" }],
      "title": "Avg Job Duration",
      "type": "stat"
    },
    {
      "datasource": { "type": "prometheus", "uid": "prometheus" },
      "fieldConfig": {
        "defaults": {
          "color": { "mode": "thresholds" },
          "mappings": [],
          "thresholds": { "mode": "absolute", "steps": [{ "color": "green", "value": null }] },
          "unit": "short"
        },
        "overrides": []
      },
      "gridPos": { "h": 4, "w": 4, "x": 12, "y": 1 },
      "id": 5,
      "options": { "colorMode": "value", "graphMode": "area", "justifyMode": "auto", "orientation": "auto", "reduceOptions": { "calcs": ["lastNotNull"], "fields": "", "values": false }, "textMode": "auto" },
      "targets": [{ "expr": "sum(spark_stage_count)", "legendFormat": "Stages", "refId": "A" }],
      "title": "Total Stages",
      "type": "stat"
    },
    {
      "datasource": { "type": "prometheus", "uid": "prometheus" },
      "fieldConfig": {
        "defaults": {
          "color": { "mode": "thresholds" },
          "mappings": [],
          "thresholds": { "mode": "absolute", "steps": [{ "color": "green", "value": null }] },
          "unit": "bytes"
        },
        "overrides": []
      },
      "gridPos": { "h": 4, "w": 4, "x": 16, "y": 1 },
      "id": 6,
      "options": { "colorMode": "value", "graphMode": "area", "justifyMode": "auto", "orientation": "auto", "reduceOptions": { "calcs": ["lastNotNull"], "fields": "", "values": false }, "textMode": "auto" },
      "targets": [{ "expr": "sum(spark_shuffle_bytes_written)", "legendFormat": "Shuffle Write", "refId": "A" }],
      "title": "Shuffle Bytes Written",
      "type": "stat"
    },
    {
      "datasource": { "type": "prometheus", "uid": "prometheus" },
      "fieldConfig": {
        "defaults": {
          "color": { "mode": "thresholds" },
          "mappings": [],
          "thresholds": { "mode": "absolute", "steps": [{ "color": "green", "value": null }] },
          "unit": "short"
        },
        "overrides": []
      },
      "gridPos": { "h": 4, "w": 4, "x": 20, "y": 1 },
      "id": 7,
      "options": { "colorMode": "value", "graphMode": "area", "justifyMode": "auto", "orientation": "auto", "reduceOptions": { "calcs": ["lastNotNull"], "fields": "", "values": false }, "textMode": "auto" },
      "targets": [{ "expr": "sum(spark_records_written)", "legendFormat": "Records Written", "refId": "A" }],
      "title": "Records Written",
      "type": "stat"
    },
    {
      "collapsed": false,
      "gridPos": { "h": 1, "w": 24, "x": 0, "y": 5 },
      "id": 8,
      "panels": [],
      "title": "Iceberg Table Metrics",
      "type": "row"
    },
    {
      "datasource": { "type": "prometheus", "uid": "prometheus" },
      "fieldConfig": {
        "defaults": {
          "color": { "mode": "palette-classic" },
          "custom": {
            "axisBorderShow": false, "axisCenteredZero": false, "axisColorMode": "text", "axisLabel": "", "axisPlacement": "auto",
            "barAlignment": 0, "drawStyle": "line", "fillOpacity": 10, "gradientMode": "none",
            "hideFrom": { "legend": false, "tooltip": false, "viz": false },
            "insertNulls": false, "lineInterpolation": "linear", "lineWidth": 1, "pointSize": 5,
            "scaleDistribution": { "type": "linear" }, "showPoints": "never", "spanNulls": false,
            "stacking": { "group": "A", "mode": "none" }, "thresholdsStyle": { "mode": "off" }
          },
          "mappings": [],
          "thresholds": { "mode": "absolute", "steps": [{ "color": "green", "value": null }] },
          "unit": "short"
        },
        "overrides": []
      },
      "gridPos": { "h": 8, "w": 12, "x": 0, "y": 6 },
      "id": 9,
      "options": {
        "legend": { "calcs": ["lastNotNull"], "displayMode": "table", "placement": "bottom", "showLegend": true },
        "tooltip": { "mode": "multi", "sort": "desc" }
      },
      "targets": [
        { "expr": "iceberg_table_snapshot_count{table=~\".*\"}", "legendFormat": "{{table}}", "refId": "A" }
      ],
      "title": "Iceberg Snapshot Count by Table",
      "type": "timeseries"
    },
    {
      "datasource": { "type": "prometheus", "uid": "prometheus" },
      "fieldConfig": {
        "defaults": {
          "color": { "mode": "palette-classic" },
          "custom": {
            "axisBorderShow": false, "axisCenteredZero": false, "axisColorMode": "text", "axisLabel": "", "axisPlacement": "auto",
            "barAlignment": 0, "drawStyle": "bars", "fillOpacity": 80, "gradientMode": "none",
            "hideFrom": { "legend": false, "tooltip": false, "viz": false },
            "insertNulls": false, "lineInterpolation": "linear", "lineWidth": 1, "pointSize": 5,
            "scaleDistribution": { "type": "linear" }, "showPoints": "never", "spanNulls": false,
            "stacking": { "group": "A", "mode": "normal" }, "thresholdsStyle": { "mode": "off" }
          },
          "mappings": [],
          "thresholds": { "mode": "absolute", "steps": [{ "color": "green", "value": null }] },
          "unit": "bytes"
        },
        "overrides": []
      },
      "gridPos": { "h": 8, "w": 12, "x": 12, "y": 6 },
      "id": 10,
      "options": {
        "legend": { "calcs": ["lastNotNull"], "displayMode": "table", "placement": "bottom", "showLegend": true },
        "tooltip": { "mode": "multi", "sort": "desc" }
      },
      "targets": [
        { "expr": "iceberg_table_size_bytes{table=~\".*\"}", "legendFormat": "{{table}}", "refId": "A" }
      ],
      "title": "Iceberg Table Size",
      "type": "timeseries"
    },
    {
      "collapsed": false,
      "gridPos": { "h": 1, "w": 24, "x": 0, "y": 14 },
      "id": 11,
      "panels": [],
      "title": "Staging Layer Metrics",
      "type": "row"
    },
    {
      "datasource": { "type": "prometheus", "uid": "prometheus" },
      "fieldConfig": {
        "defaults": {
          "color": { "mode": "palette-classic" },
          "custom": {
            "axisBorderShow": false, "axisCenteredZero": false, "axisColorMode": "text", "axisLabel": "", "axisPlacement": "auto",
            "barAlignment": 0, "drawStyle": "line", "fillOpacity": 20, "gradientMode": "none",
            "hideFrom": { "legend": false, "tooltip": false, "viz": false },
            "insertNulls": false, "lineInterpolation": "smooth", "lineWidth": 2, "pointSize": 5,
            "scaleDistribution": { "type": "linear" }, "showPoints": "never", "spanNulls": true,
            "stacking": { "group": "A", "mode": "none" }, "thresholdsStyle": { "mode": "off" }
          },
          "mappings": [],
          "thresholds": { "mode": "absolute", "steps": [{ "color": "green", "value": null }] },
          "unit": "short"
        },
        "overrides": []
      },
      "gridPos": { "h": 8, "w": 12, "x": 0, "y": 15 },
      "id": 12,
      "options": {
        "legend": { "calcs": ["sum"], "displayMode": "table", "placement": "bottom", "showLegend": true },
        "tooltip": { "mode": "multi", "sort": "desc" }
      },
      "targets": [
        { "expr": "increase(staging_records_processed{table=~\".*\"}[1h])", "legendFormat": "{{table}}", "refId": "A" }
      ],
      "title": "Records Processed (1h)",
      "type": "timeseries"
    },
    {
      "datasource": { "type": "prometheus", "uid": "prometheus" },
      "fieldConfig": {
        "defaults": {
          "color": { "mode": "palette-classic" },
          "custom": {
            "axisBorderShow": false, "axisCenteredZero": false, "axisColorMode": "text", "axisLabel": "", "axisPlacement": "auto",
            "barAlignment": 0, "drawStyle": "line", "fillOpacity": 10, "gradientMode": "none",
            "hideFrom": { "legend": false, "tooltip": false, "viz": false },
            "insertNulls": false, "lineInterpolation": "linear", "lineWidth": 1, "pointSize": 5,
            "scaleDistribution": { "type": "linear" }, "showPoints": "never", "spanNulls": false,
            "stacking": { "group": "A", "mode": "none" }, "thresholdsStyle": { "mode": "off" }
          },
          "mappings": [],
          "thresholds": { "mode": "absolute", "steps": [{ "color": "green", "value": null }] },
          "unit": "s"
        },
        "overrides": []
      },
      "gridPos": { "h": 8, "w": 12, "x": 12, "y": 15 },
      "id": 13,
      "options": {
        "legend": { "calcs": ["mean", "max"], "displayMode": "table", "placement": "bottom", "showLegend": true },
        "tooltip": { "mode": "multi", "sort": "desc" }
      },
      "targets": [
        { "expr": "staging_job_duration_seconds{table=~\".*\"}", "legendFormat": "{{table}}", "refId": "A" }
      ],
      "title": "Staging Job Duration",
      "type": "timeseries"
    }
  ],
  "refresh": "30s",
  "schemaVersion": 38,
  "tags": ["batch", "spark", "iceberg", "staging"],
  "templating": { "list": [] },
  "time": { "from": "now-6h", "to": "now" },
  "timepicker": {},
  "timezone": "browser",
  "title": "Batch Processing Metrics",
  "uid": "batch-metrics-dashboard",
  "version": 1,
  "weekStart": ""
}
